pydeepxlsx/__init__.py
pydeepxlsx-1.0.4.dist-info/LICENSE
pydeepxlsx-1.0.4.dist-info/METADATA
pydeepxlsx-1.0.4.dist-info/WHEEL
pydeepxlsx-1.0.4.dist-info/top_level.txt
pydeepxlsx-1.0.4.dist-info/RECORD
