Metadata-Version: 2.1
Name: pydeepxlsx
Version: 1.0.4
Summary: XLSX file as a template
Home-page: https://www.python.org/sigs/distutils-sig/
Author: WildSys
Author-email: WildSys <hello@wildsys.io>
Project-URL: Homepage, https://github.com/wildsys/pydeepxlsx
Project-URL: Bug Tracker, https://github.com/wildsys/pydeepxlsx/issues
Keywords: xlsx,copy
Classifier: Development Status :: 3 - Alpha
Classifier: Programming Language :: Python :: 3
Classifier: Operating System :: OS Independent
Requires-Python: >=3.9
License-File: LICENSE
Requires-Dist: openpyxl <3.1,>=3.0
Requires-Dist: python-slugify <8.1,>=8.0
